ebrains_validation_framework/__init__.py
ebrains_validation_framework/cli.py
ebrains_validation_framework/datastores.py
ebrains_validation_framework/sample.py
ebrains_validation_framework/utils.py
ebrains_validation_framework/versioning.py
ebrains_validation_framework/jsonTreeViewer/CHANGELOG.md
ebrains_validation_framework/jsonTreeViewer/LICENSE
ebrains_validation_framework/jsonTreeViewer/README.md
ebrains_validation_framework/jsonTreeViewer/document.json
ebrains_validation_framework/jsonTreeViewer/favicon.ico
ebrains_validation_framework/jsonTreeViewer/index.htm
ebrains_validation_framework/jsonTreeViewer/jsonTreeViewer.js
ebrains_validation_framework/jsonTreeViewer/libs/app/App.js
ebrains_validation_framework/jsonTreeViewer/libs/app/README.md
ebrains_validation_framework/jsonTreeViewer/libs/app/app.css
ebrains_validation_framework/jsonTreeViewer/libs/app/reset.css
ebrains_validation_framework/jsonTreeViewer/libs/app/docs/index.htm
ebrains_validation_framework/jsonTreeViewer/libs/app/docs/main.css
ebrains_validation_framework/jsonTreeViewer/libs/jsonTree/icons.svg
ebrains_validation_framework/jsonTreeViewer/libs/jsonTree/jsonTree.css
ebrains_validation_framework/jsonTreeViewer/libs/jsonTree/jsonTree.js
ebrains_validation_framework/templates/report_template.html
ebrains_validation_framework-0.9.3.dist-info/licenses/LICENSE.txt
ebrains_validation_framework-0.9.3.dist-info/METADATA
ebrains_validation_framework-0.9.3.dist-info/WHEEL
ebrains_validation_framework-0.9.3.dist-info/top_level.txt
ebrains_validation_framework-0.9.3.dist-info/RECORD
