Metadata-Version: 2.4
Name: ebrains_validation_framework
Version: 0.9.3
Summary: Python client for the EBRAINS Validation Framework web services.
Author-email: "Andrew P. Davison" <andrew.davison@cnrs.fr>, Shailesh Appukuttan <appukuttan.shailesh@gmail.com>
License-Expression: BSD-3-Clause
Project-URL: Homepage, https://github.com/HumanBrainProject/ebrains-validation-client
Keywords: ebrains,hbp,model validation
Classifier: Development Status :: 4 - Beta
Classifier: Intended Audience :: Science/Research
Classifier: Topic :: Scientific/Engineering
Classifier: Programming Language :: Python :: 3
Requires-Python: >=3.8
License-File: LICENSE.txt
Requires-Dist: requests
Requires-Dist: nameparser
Requires-Dist: ebrains_drive
Provides-Extra: reports
Requires-Dist: Jinja2; extra == "reports"
Requires-Dist: pyppdf; extra == "reports"
Requires-Dist: beautifulsoup4; extra == "reports"
Requires-Dist: hbp_archive; extra == "reports"
Provides-Extra: utils
Requires-Dist: sciunit; extra == "utils"
Dynamic: license-file
